<?xml version='1.0' encoding='utf-8'?>

<!-- Created with Lineage II - Multisell Manager -->
<!-- © 2007 by tReXpert -->

<list maintainEnchantment="true">

  <!-- Majestic Necklace -->
	<item id="1">
		 
		<production id="924" count="1" enchant="4" />
	</item>
	<item id="2">
		<production id="862" count="1" enchant="4" />
	</item>
	<item id="3">
		<production id="893" count="1" enchant="4" />
	</item>

  <!-- Phoenix Necklace -->
	<item id="4">
		<production id="933" count="1" enchant="4" />
	</item>
	<item id="5">
		<production id="871" count="1" enchant="4" />
	</item>
	<item id="6">
		<production id="902" count="1" enchant="4" />
	</item>


</list>
